{"type":"FeatureCollection","features":[{"type":"Feature","geometry":{"type":"Point","coordinates":[-79.512566188931,43.616187795106]},"properties":{"youtube:link":"","co2e":"0","weight":"0","unit":"kg","qty":"0","supplychain_instance_id":"supplychain-1","stop_instance_id":"stop-4","description":"","address":"Etobicoke, Toronto, ON, Canada","title":"D"}},{"type":"Feature","geometry":{"type":"Point","coordinates":[-83.04575378844,42.331426995183]},"properties":{"supplychain_instance_id":"supplychain-1","stop_instance_id":"stop-3","description":"","address":"Detroit, MI, USA","title":"XPS panels"}},{"type":"Feature","geometry":{"type":"Point","coordinates":[-73.553992489761,45.508669895003]},"properties":{"supplychain_instance_id":"supplychain-1","stop_instance_id":"stop-2","description":"","address":"Montreal, QC, Canada","title":"polyeurethane insulation"}},{"type":"Feature","geometry":{"type":"Point","coordinates":[-80.494703388795,43.444152295115]},"properties":{"youtube:link":"","co2e":"0","weight":"0","unit":"kg","qty":"0","supplychain_instance_id":"supplychain-1","stop_instance_id":"stop-1","description":"construction site","address":"20 Mill St, Kitchener, ON N2G 2Y2, Canada","title":"REEP House"}}],"properties":{"title":"REEP House","description":"","tags":""}}