{"type":"FeatureCollection","features":[{"type":"Feature","geometry":{"type":"Point","coordinates":[-108.4898506849,45.793132794989]},"properties":{"youtube:link":"","co2e":"0","weight":"0","unit":"kg","qty":"0","supplychain_instance_id":"supplychain-1","stop_instance_id":"stop-1","description":"We combine the best construction techniques technology has to offer with the keen eye and hands of a craftsman.  We build every bag right here in Billings, Montana, under the strict supervision of experienced parachute riggers.  Every stitch on every piece going out the door gets the same attention as those thousands of parachutes that landed our troopers gently on the ground. \n\nSince our founding, Red Oxx has worked to improve everything in our line, every year.  Today our travel gear enjoys a reputation unlike any other; rugged construction, dependable design, and built to endure any amount of abuse in any location in the world.  \n\nOur plan is simple.  Stick to what we know, do it better than it\u2019s ever been before, and stay true to our customers.  The results have spoken for themselves, and Red Oxx has successfully developed a unique line of premium travel gear and bags that live up to their potential, one adventure at a time.","address":"310 N 13th St, Billings, Mt 59101, USA","title":"Red Oxx Mfg. Inc."}}],"properties":{"title":"Red Oxx Mfg. Inc.","description":"Red Oxx sells handcrafted, soft-sided luggage to customers across the globe.  Visit redoxx.com to learn more. ","tags":""}}