{"type":"FeatureCollection","features":[{"type":"Feature","geometry":{"type":"Point","coordinates":[-114.050003,50.984501]},"properties":{"url:moreinfo":"http:\/\/foodtree.com\/sources\/771","urltitle:moreinfo":"Please visit Calgary Farmers Market on Foodtree","address":"510 77th Avenue SE, Calgary, Alberta, Canada, T2H 1C3","title":"Calgary Farmers Market"}},{"type":"Feature","geometry":{"type":"Point","coordinates":[-114.001999,50.9856]},"properties":{"url:moreinfo":"http:\/\/foodtree.com\/sources\/852","urltitle:moreinfo":"Please visit Shef's Fiery Kitchen Inc. on Foodtree","address":"7431 24th Street SE, Calgary, Alberta, Canada, T2C 0Y7","title":"Shef's Fiery Kitchen Inc."}}],"properties":{"title":"Shef's Fiery Kitchen Inc. - connections"}}