{"type":"FeatureCollection","features":[{"type":"Feature","geometry":{"type":"Point","coordinates":[-87.590599,41.7841]},"properties":{"url:moreinfo":"http:\/\/foodtree.com\/sources\/2586","urltitle:moreinfo":"Please visit 61st Street Farmers Market on Foodtree","address":"6100 S. Blackstone Ave., Cook, Chicago, ILLINOIS, USA, 60637","title":"61st Street Farmers Market"}},{"type":"Feature","geometry":{"type":"Point","coordinates":[-87.697098,41.895401]},"properties":{"url:moreinfo":"http:\/\/foodtree.com\/sources\/5664","urltitle:moreinfo":"Please visit Patchwork Farm on Foodtree","address":"2805 W Chicago Ave, Chicago, Illinois, United States, 60612","title":"Patchwork Farm"}}],"properties":{"title":"Patchwork Farm - connections"}}