{"type":"FeatureCollection","features":[{"type":"Feature","geometry":{"type":"Point","coordinates":[-123.193001,49.133801]},"properties":{"url:moreinfo":"http:\/\/foodtree.com\/sources\/5684","urltitle:moreinfo":"Please visit Blessed Bee Farm on Foodtree","address":"2871 Steveston Hwy, Richmond, British Columbia, Canada, V7E 2J1","title":"Blessed Bee Farm"}}],"properties":{"title":"Blessed Bee Farm - connections"}}