{"type":"FeatureCollection","features":[{"type":"Feature","geometry":{"type":"Point","coordinates":[-123.107002,49.2631]},"properties":{"url:moreinfo":"http:\/\/foodtree.com\/sources\/5992","urltitle:moreinfo":"Please visit La Gioia Events on Foodtree","address":"123 Broadway, Vancouver, BC, Canada","title":"La Gioia Events"}}],"properties":{"title":"La Gioia Events - connections"}}