{"type":"FeatureCollection","features":[{"type":"Feature","geometry":{"type":"Point","coordinates":[-123.063004,49.279701]},"properties":{"url:moreinfo":"http:\/\/foodtree.com\/sources\/269","urltitle:moreinfo":"Please visit Farmstead Wines on Foodtree","address":"2016 Ferndale Street, Vancouver, British Columbia, Canada","title":"Farmstead Wines"}},{"type":"Feature","geometry":{"type":"Point","coordinates":[15.7391,48.4716]},"properties":{"url:moreinfo":"http:\/\/foodtree.com\/sources\/304","urltitle:moreinfo":"Please visit Martin Arndorfer on Foodtree","address":"Weinbergweg 16, Strass, Kamptal, Austria","title":"Martin Arndorfer"}}],"properties":{"title":"Martin Arndorfer - connections"}}