{"type":"FeatureCollection","features":[{"type":"Feature","geometry":{"type":"Point","coordinates":[-75.862396,42.166698]},"properties":{"url:moreinfo":"http:\/\/foodtree.com\/sources\/6747","urltitle:moreinfo":"Please visit Old Barn Hollow Farm on Foodtree","address":"Chenago Bridge, Chenango, NY, USA, 13901","title":"Old Barn Hollow Farm"}}],"properties":{"title":"Old Barn Hollow Farm - connections"}}