{"type":"FeatureCollection","features":[{"type":"Feature","geometry":{"type":"Point","coordinates":[-123.179001,49.232601]},"properties":{"url:moreinfo":"http:\/\/foodtree.com\/sources\/6749","urltitle:moreinfo":"Please visit Urban Digs Farm on Foodtree","address":"5930 Blenheim St., Vancouver, BC, Canada, V6N 1R1","title":"Urban Digs Farm"}}],"properties":{"title":"Urban Digs Farm - connections"}}