{"type":"FeatureCollection","features":[{"type":"Feature","geometry":{"type":"Point","coordinates":[-85.597298,42.303398]},"properties":{"url:moreinfo":"http:\/\/foodtree.com\/sources\/6923","urltitle:moreinfo":"Please visit Douglass Farmers' Market on Foodtree","address":"1000 W. Paterson Street, Kalamazoo, Michigan, United States, 49007","title":"Douglass Farmers' Market"}}],"properties":{"title":"Douglass Farmers' Market - connections"}}