{"type":"FeatureCollection","features":[{"type":"Feature","geometry":{"type":"Point","coordinates":[-114.053001,51.0173]},"properties":{"url:moreinfo":"http:\/\/foodtree.com\/sources\/5987","address":"540 Cleveland Cres SE, Calgary, Alberta, Canada, T2G 4R8","title":"Ukrainian Fine Foods"}},{"type":"Feature","geometry":{"type":"Point","coordinates":[-113.478996,53.447399]},"properties":{"url:moreinfo":"http:\/\/foodtree.com\/sources\/1084","address":"151 Karl Clark Road, Edmonton, Alberta, Canada, T6N 0A4","title":"Strawberry Creek Farms"}},{"type":"Feature","geometry":{"type":"Point","coordinates":[-111.866997,53.4562]},"properties":{"url:moreinfo":"http:\/\/foodtree.com\/sources\/5985","address":"Box 125  5125 51 Avenue, Lavoy, Alberta, Canada, (780) 658-3330","title":"Skyline Greenhouse"}},{"type":"Feature","geometry":{"type":"Point","coordinates":[-113.478996,53.447399]},"properties":{"url:moreinfo":"http:\/\/foodtree.com\/sources\/5986","address":"151 Karl Clark Road, Edmonton, British Columbia, Canada, T6N 1H5","title":"Shergood Gardens Farm"}},{"type":"Feature","geometry":{"type":"Point","coordinates":[-124.487,49.8335]},"properties":{"url:moreinfo":"http:\/\/foodtree.com\/sources\/891","address":"4202 Myrtle Ave, Powell River, British Columbia, Canada","title":"Steve & Dan's Fresh BC Fruit"}},{"type":"Feature","geometry":{"type":"Point","coordinates":[-113.478996,53.447399]},"properties":{"url:moreinfo":"http:\/\/foodtree.com\/sources\/1067","address":"151 Karl Clark Road, Edmonton, Alberta, Canada, T6N 1H5","title":"South Common Farmers Market"}}],"properties":{"title":"South Common Farmers Market"}}