{"type":"FeatureCollection","features":[{"type":"Feature","geometry":{"type":"Point","coordinates":[-114.066002,50.898102]},"properties":{"url:moreinfo":"http:\/\/foodtree.com\/sources\/779","address":"South Arena Lot, 333 Shawville Blvd. S.E., Calgary, Alberta, Canada, T2Y 4H3","title":"South Fish Creek Farmers' Market"}}],"properties":{"title":"South Fish Creek Farmers' Market"}}