{"type":"FeatureCollection","features":[{"type":"Feature","geometry":{"type":"Point","coordinates":[-155.080002,19.715599]},"properties":{"url:moreinfo":"http:\/\/foodtree.com\/sources\/7446","address":"100 Barenaba Lane, Hilo, HI, United States, 96720","title":"Big Island Farm Fresh Foods"}}],"properties":{"title":"Big Island Farm Fresh Foods"}}