{"type":"FeatureCollection","features":[{"type":"Feature","geometry":{"type":"Point","coordinates":[-77.142601,44.006802]},"properties":{"url:moreinfo":"http:\/\/foodtree.com\/sources\/1048","address":"172 Main Street, Picton, Ontario, Canada","title":"Buddha Dog"}},{"type":"Feature","geometry":{"type":"Point","coordinates":[-79.434303,43.657101]},"properties":{"url:moreinfo":"http:\/\/foodtree.com\/sources\/1081","address":"873 Dufferin Street, Toronto, Ontario, Canada, M6H 4B2","title":"Dufferin Grove Organic Farmers Market"}}],"properties":{"title":"Dufferin Grove Organic Farmers Market"}}