{"type":"FeatureCollection","features":[{"type":"Feature","geometry":{"type":"Point","coordinates":[-96.820999,32.951199]},"properties":{"url:moreinfo":"http:\/\/foodtree.com\/sources\/6521","address":"5100 Belt Line Rd, Dallas, Dallas, TEXAS, USA, 75254","title":"Four Seasons Markets at Addison"}}],"properties":{"title":"Four Seasons Markets at Addison - connections"}}