{"type":"FeatureCollection","features":[{"type":"Feature","geometry":{"type":"Point","coordinates":[-73.989799,40.757198]},"properties":{"url:moreinfo":"http:\/\/foodtree.com\/sources\/2650","address":"42nd Street & 8th Ave, New York, NEW YORK, USA, 10036","title":"Port Authority Bus Terminal Greenmarket"}},{"type":"Feature","geometry":{"type":"Point","coordinates":[-122.646004,45.559101]},"properties":{"url:moreinfo":"http:\/\/foodtree.com\/sources\/7696","address":"1829 NE Alberta, Suite 5, Portland, OR, US, 97211","title":"Food Alliance"}},{"type":"Feature","geometry":{"type":"Point","coordinates":[-73.697899,42.395401]},"properties":{"url:moreinfo":"http:\/\/foodtree.com\/sources\/5454","address":"34 Fischer Road Extension, Kinderhook, NY, USA, 12106","title":"Katchkie Farm"}}],"properties":{"title":"Katchkie Farm - connections"}}