{"type":"FeatureCollection","features":[{"type":"Feature","geometry":{"type":"Point","coordinates":[-123.115997,49.287701]},"properties":{"url:moreinfo":"http:\/\/foodtree.com\/sources\/8648","address":"1001 West Cordova Street, Vancouver, British Columbia, Canada, V6C 0B7","title":"Bella Gelateria"}},{"type":"Feature","geometry":{"type":"Point","coordinates":[-123.028,49.2729]},"properties":{"url:moreinfo":"http:\/\/foodtree.com\/sources\/6687","address":"1315 Kootenay Street, Vancouver, British Columbia, Canada, V5K 4Y3","title":"Ethical Bean"}},{"type":"Feature","geometry":{"type":"Point","coordinates":[-123.122002,49.2785]},"properties":{"url:moreinfo":"http:\/\/foodtree.com\/sources\/7700","address":"1002 Seymour Street, Vancouver, British Columbia, Canada, V6B 3M6","title":"Commune Cafe"}},{"type":"Feature","geometry":{"type":"Point","coordinates":[-123.124001,49.2775]},"properties":{"url:moreinfo":"http:\/\/foodtree.com\/sources\/8649","address":"1102 Seymour Street, Vancouver, British Columbia, Canada, V6B 5B6","title":"It's To Die For Banana Bread"}}],"properties":{"title":"It's To Die For Banana Bread"}}