{"type":"FeatureCollection","features":[{"type":"Feature","geometry":{"type":"Point","coordinates":[-81.10892398871,43.870090995091]},"properties":{"description":"","address":"Gorrie, ON N0G, Canada","title":"Howick Central School"}}],"properties":{"title":"Disposable Diapers","description":"","tags":"","sm:ui:weight":"1","sm:ui:co2e":"1","sm:ui:water":"1","sm:ui:energy":"1"}}