{"type":"FeatureCollection","features":[{"type":"Feature","geometry":{"type":"Point","coordinates":[-75.226027989529,40.028890495337]},"properties":{"description":"","address":"Philadelphia, PA 19127, USA","title":"Waskerd Studio"}}],"properties":{"title":"Waskerd Handcrafted Leather Wallets","description":"Waskerd goods are handcrafted in Philadelphia by Derek Shaw. He does every step ","tags":""}}