{"type":"FeatureCollection","features":[{"type":"Feature","geometry":{"type":"Point","coordinates":[-0.56729379992104,44.825989395039]},"properties":{"description":"","address":"81 Rue de B\u00e8gles, 33800 Bordeaux, France","title":"maison"}}],"properties":{"title":"bender","description":"yo","tags":""}}