{"type":"FeatureCollection","features":[{"type":"Feature","geometry":{"type":"Point","coordinates":[-73.167351,44.015329]},"properties":{"url:moreinfo":"http:\/\/foodtree.com\/sources\/9676","urltitle:moreinfo":"Please visit Vermont Coffee Company on Foodtree","address":"1197 Exchange Street, #3,  Middlebury, Vermont, USA, 05753","title":"Vermont Coffee Company"}},{"type":"Feature","geometry":{"type":"Point","coordinates":[-73.202003,44.489101]},"properties":{"url:moreinfo":"http:\/\/foodtree.com\/sources\/6021","urltitle:moreinfo":"Please visit Sugarsnap on Foodtree","address":"30 Community Drive, South Burlington, VT, United States, 05401","title":"Sugarsnap"}},{"type":"Feature","geometry":{"type":"Point","coordinates":[-73.202003,44.489101]},"properties":{"url:moreinfo":"http:\/\/foodtree.com\/sources\/9669","urltitle:moreinfo":"Please visit Sugarsnap Farm on Foodtree","address":"505 Riverside Avenue, Burlington, VT, United States, 05401","title":"Sugarsnap Farm"}},{"type":"Feature","geometry":{"type":"Point","coordinates":[-73.22098,44.476605]},"properties":{"url:moreinfo":"http:\/\/foodtree.com\/sources\/11062","urltitle:moreinfo":"Please visit Sugarsnap at Echo on Foodtree","address":"1 College Street, Burlington, Vermont, USA, 5401","title":"Sugarsnap at Echo"}}],"properties":{"title":"Sugarsnap at Echo - connections"}}