{"type":"FeatureCollection","features":[{"type":"Feature","geometry":{"type":"Point","coordinates":[-121.935997,49.108101]},"properties":{"url:moreinfo":"http:\/\/foodtree.com\/sources\/5894","address":"5828 Promontory Road, Chilliwack, British Columbia, Canada, V2R4M4","title":"Johnston's Fresh Local Quality Meats"}},{"type":"Feature","geometry":{"type":"Point","coordinates":[-122.007004,49.119701]},"properties":{"url:moreinfo":"http:\/\/foodtree.com\/sources\/5787","address":"5787 Lickman Road, Chilliwack, British Columbia, Canada, V2R4B5","title":"Smits & Co.w Farm Cheese"}},{"type":"Feature","geometry":{"type":"Point","coordinates":[-121.851997,49.157101]},"properties":{"url:moreinfo":"http:\/\/foodtree.com\/sources\/5895","address":"8565 Upper Prairie Road, Chilliwack, British Columbia, Canada, V2P6H3","title":"Verard Farms"}}],"properties":{"title":"Verard Farms"}}