{"type":"FeatureCollection","features":[{"type":"Feature","geometry":{"type":"Point","coordinates":[-122.629997,45.504902]},"properties":{"url:moreinfo":"http:\/\/foodtree.com\/sources\/5758","urltitle:moreinfo":"Please visit Stumptown Coffee Roasters on Foodtree","address":"3377 SE Division Street, Suite 101, Portland, Oregon, USA, 97202","title":"Stumptown Coffee Roasters"}},{"type":"Feature","geometry":{"type":"Point","coordinates":[-122.654999,45.5047]},"properties":{"url:moreinfo":"http:\/\/foodtree.com\/sources\/7280","urltitle:moreinfo":"Please visit Foxfire Tea Company on Foodtree","address":"2505 SE 11th Ave, #105, Portland, Oregon, USA, 97202","title":"Foxfire Tea Company"}},{"type":"Feature","geometry":{"type":"Point","coordinates":[-122.648003,45.512199]},"properties":{"url:moreinfo":"http:\/\/foodtree.com\/sources\/10108","urltitle:moreinfo":"Please visit Oui Presse on Foodtree","address":"1740 Southeast Hawthorne Boulevard, Portland, Oregon, USA, 97214","title":"Oui Presse"}}],"properties":{"title":"Oui Presse - connections"}}