{"type":"FeatureCollection","features":[{"type":"Feature","geometry":{"type":"Point","coordinates":[6.5463155990887,0.28828959995986]},"properties":{"description":"","address":"Pico de S\u00e3o Tom\u00e9, S\u00e3o Tom\u00e9 and Pr\u00edncipe","title":"\u3066\uff53\uff54"}}],"properties":{"title":"\u6c5f\u5742\u5468\u8fba","description":"\u6c5f\u5742\u5468\u8fba\u306e\u55ab\u8336\u5e97\u306a\u3069","tags":""}}