{"type":"FeatureCollection","features":[{"type":"Feature","geometry":{"type":"Point","coordinates":[-122.646004,45.559101]},"properties":{"url:moreinfo":"http:\/\/foodtree.com\/sources\/7696","urltitle:moreinfo":"Please visit Food Alliance on Foodtree","address":"1829 NE Alberta, Suite 5, Portland, OR, US, 97211","title":"Food Alliance"}},{"type":"Feature","geometry":{"type":"Point","coordinates":[-123.169451,44.598514]},"properties":{"url:moreinfo":"http:\/\/foodtree.com\/sources\/7584","urltitle:moreinfo":"Please visit Rain Sheep on Foodtree","address":"35169 Riverside Dr SW, Albany, Oregon, USA, 97321","title":"Rain Sheep"}}],"properties":{"title":"Rain Sheep - connections"}}