{"type":"FeatureCollection","features":[{"type":"Feature","geometry":{"type":"Point","coordinates":[-123.100998,49.264599]},"properties":{"description":"Apple","url:moreinfo":"http:\/\/foodtree.com\/sources\/5218","address":"1 Kingsway, Vancouver, British Columbia, Canada, V5T 3H7","title":"Mount Pleasant Community"}}],"properties":{"title":"Mount Pleasant Community - connections"}}