{"type":"FeatureCollection","features":[{"type":"Feature","geometry":{"type":"Point","coordinates":[-122.646004,45.559101]},"properties":{"url:moreinfo":"http:\/\/foodtree.com\/sources\/7696","address":"1829 NE Alberta, Suite 5, Portland, OR, US, 97211","title":"Food Alliance"}},{"type":"Feature","geometry":{"type":"Point","coordinates":[-122.661003,45.638699]},"properties":{"url:moreinfo":"http:\/\/foodtree.com\/sources\/7650","address":"Vancouver, Washington, USA, 98660","title":"Hearth of vancouver"}}],"properties":{"title":"Hearth of vancouver"}}