{"type":"FeatureCollection","features":[{"type":"Feature","geometry":{"type":"Point","coordinates":[-87.629204,41.895]},"properties":{"url:moreinfo":"http:\/\/foodtree.com\/sources\/9778","address":"30 West Huron St, Chicago, IL, United States, 60654","title":"Whole Foods Market  Gold Coast"}}],"properties":{"title":"Whole Foods Market  Gold Coast"}}