{"type":"FeatureCollection","features":[{"type":"Feature","geometry":{"type":"Point","coordinates":[-96.840292,32.800119]},"properties":{"url:moreinfo":"http:\/\/foodtree.com\/sources\/15351","address":"2505 Farrington, Dallas, Texas, USA, 75207","title":"Village Baking Co"}},{"type":"Feature","geometry":{"type":"Point","coordinates":[-97.227105,32.930039]},"properties":{"url:moreinfo":"http:\/\/foodtree.com\/sources\/6529","address":"1100 Bear Creek Parkway, Keller, Texas, USA, 76248","title":"Keller Farmer's Market"}}],"properties":{"title":"Keller Farmer's Market"}}