{"type":"FeatureCollection","features":[{"type":"Feature","geometry":{"type":"Point","coordinates":[-123.310171,42.436566]},"properties":{"url:moreinfo":"http:\/\/foodtree.com\/sources\/15921","urltitle:moreinfo":"Please visit Grants Pass Growers Market on Foodtree","address":"F St  , Grants Pass, OR , United States, 97526","title":"Grants Pass Growers Market"}}],"properties":{"title":"Grants Pass Growers Market - connections"}}