{"type":"FeatureCollection","features":[{"type":"Feature","geometry":{"type":"Point","coordinates":[-74.005973089698,40.714352795289]},"properties":{"description":"","address":"New York, NY, USA","title":"Aveda store"}}],"properties":{"description":"","tags":"","title":"face cream"}}