{"type":"FeatureCollection","features":[{"type":"Feature","geometry":{"type":"Point","coordinates":[-80.226439288832,25.788968896653]},"properties":{"description":"","address":"Miami, FL, USA","title":"Miami"}},{"type":"Feature","geometry":{"type":"Point","coordinates":[148.99231073459,25.788968896653]},"properties":{"supplychain_instance_id":"supplychain-1","stop_instance_id":"stop-1","description":"","address":"25.7889689,-211.00768929478","title":"Miami"}}],"properties":{"description":"","tags":"","title":"Banks Global Transport, Inc."}}