{"type":"FeatureCollection","features":[{"type":"Feature","geometry":{"type":"Point","coordinates":[-73.389581,42.208659]},"properties":{"url:moreinfo":"http:\/\/foodtree.com\/sources\/32591","urltitle:moreinfo":"Please visit HimalaSalt on Foodtree","address":"P.O. Box 900, Great Barrington, MA, US, 01230","title":"HimalaSalt"}}],"properties":{"title":"HimalaSalt - connections"}}