{"type":"FeatureCollection","features":[{"type":"Feature","geometry":{"type":"Point","coordinates":[-72.371635,44.671259]},"properties":{"url:moreinfo":"http:\/\/foodtree.com\/sources\/32681","urltitle:moreinfo":"Please visit Michelle's Spicy Kimchi on Foodtree","address":"832 Mill Village Road, Craftsbury Common, Vermont, US, 05827","title":"Michelle's Spicy Kimchi"}},{"type":"Feature","geometry":{"type":"Point","coordinates":[-72.591271,44.572126]},"properties":{"url:moreinfo":"http:\/\/foodtree.com\/sources\/32721","urltitle:moreinfo":"Please visit Apple Tree Natural Foods Market on Foodtree","address":"30 Mountain View Plz # 2, Morrisville, VT, US, 05661","title":"Apple Tree Natural Foods Market"}}],"properties":{"title":"Apple Tree Natural Foods Market - connections"}}