{"type":"FeatureCollection","features":[{"type":"Feature","geometry":{"type":"Point","coordinates":[-72.540646,43.063968]},"properties":{"url:moreinfo":"http:\/\/foodtree.com\/sources\/15041","urltitle:moreinfo":"Please visit Vermont Cheese Council on Foodtree","address":"Westminster West, Vermont, USA","title":"Vermont Cheese Council"}},{"type":"Feature","geometry":{"type":"Point","coordinates":[-73.25183,44.167837]},"properties":{"url:moreinfo":"http:\/\/foodtree.com\/sources\/10892","urltitle:moreinfo":"Please visit Graze on Foodtree","address":"10 Green Street, Vergennes, VT, USA, 05443","title":"Graze"}},{"type":"Feature","geometry":{"type":"Point","coordinates":[-72.757896,44.921009]},"properties":{"url:moreinfo":"http:\/\/foodtree.com\/sources\/32801","urltitle:moreinfo":"Please visit Boston Post Dairy, LLC on Foodtree","address":"2061 Sampsonville Road, Enosburg Falls, VT, US, 05450","title":"Boston Post Dairy, LLC"}}],"properties":{"title":"Boston Post Dairy, LLC"}}