{"type":"FeatureCollection","features":[{"type":"Feature","geometry":{"type":"Point","coordinates":[108.27719898493,14.058323998082]},"properties":{"youtube:link":"","water":"0","energy":"0","co2e":"0","weight":"1","supplychain_instance_id":"supplychain-1","stop_instance_id":"stop-42","description":"","address":"Vietnam","title":"Rice"}}],"properties":{"description":"","tags":"","title":"Long-Distance Burrito"}}