{"type":"FeatureCollection","features":[{"type":"Feature","geometry":{"type":"Point","coordinates":[-122.27111368298,37.804363695503]},"properties":{"description":"","address":"Oakland, CA, USA","title":"oakland CA"}}],"properties":{"description":"","tags":"","title":"pasta alfredo"}}