{"type":"FeatureCollection","features":[{"type":"Feature","geometry":{"type":"Point","coordinates":[-73.213898,44.4589]},"properties":{"url:moreinfo":"http:\/\/foodtree.com\/sources\/8139","urltitle:moreinfo":"Please visit Lake Champlain Chocolates on Foodtree","address":"750 Pine Street, Burlington, VT, 05401, United States","title":"Lake Champlain Chocolates"}},{"type":"Feature","geometry":{"type":"Point","coordinates":[-84.320396,39.3078]},"properties":{"url:moreinfo":"http:\/\/foodtree.com\/sources\/9816","urltitle:moreinfo":"Please visit Whole Foods Market  Mason on Foodtree","address":"5805 Deerfield Blvd, Mason, OH, 45040, United States","title":"Whole Foods Market  Mason"}}],"properties":{"title":"Whole Foods Market  Mason - connections"}}