{"type":"FeatureCollection","features":[{"type":"Feature","geometry":{"type":"Point","coordinates":[-122.646004,45.559101]},"properties":{"url:moreinfo":"http:\/\/foodtree.com\/sources\/7696","urltitle:moreinfo":"Please visit Food Alliance on Foodtree","address":"1829 NE Alberta, Suite 5, Portland, OR, 97211, US","title":"Food Alliance"}},{"type":"Feature","geometry":{"type":"Point","coordinates":[-119.289001,45.840401]},"properties":{"url:moreinfo":"http:\/\/foodtree.com\/sources\/7503","urltitle:moreinfo":"Please visit Finley's Fresh Produce, LLC on Foodtree","address":"80728 Cooney Lane, Hermiston, OR, 97838, USA","title":"Finley's Fresh Produce, LLC"}}],"properties":{"title":"Finley's Fresh Produce, LLC - connections"}}