{"type":"FeatureCollection","features":[{"type":"Feature","geometry":{"type":"Point","coordinates":[-123.538111,48.370309]},"properties":{"url:moreinfo":"http:\/\/foodtree.com\/sources\/36251","urltitle:moreinfo":"Please visit Wind Whipped Farm on Foodtree","address":"4645 B William Head Road, Victoria, BC, Canada","title":"Wind Whipped Farm"}}],"properties":{"title":"Wind Whipped Farm - connections"}}