{"type":"FeatureCollection","features":[{"type":"Feature","geometry":{"type":"Point","coordinates":[-77.3946,39.035]},"properties":{"url:moreinfo":"http:\/\/foodtree.com\/sources\/9213","urltitle:moreinfo":"Please visit LVHMA Cascades Farmers Market on Foodtree","address":"20160 Whitfield Pl, Sterling, Virginia, USA, 20165","title":"LVHMA Cascades Farmers Market"}}],"properties":{"title":"LVHMA Cascades Farmers Market"}}