{"type":"FeatureCollection","features":[{"type":"Feature","geometry":{"type":"Point","coordinates":[-123.103996,49.2813]},"properties":{"url:moreinfo":"http:\/\/foodtree.com\/sources\/6699","urltitle:moreinfo":"Please visit Penn Bakeshop on Foodtree","address":"408 Carrall Street, Vancouver, British Columbia, Canada, V6B 2J7","title":"Penn Bakeshop"}},{"type":"Feature","geometry":{"type":"Point","coordinates":[-123.105003,49.2812]},"properties":{"url:moreinfo":"http:\/\/foodtree.com\/sources\/7701","urltitle:moreinfo":"Please visit Fetch on Foodtree","address":"425 Carrall Street, Vancouver, British Columbia, Canada, V6B6E3","title":"Fetch"}}],"properties":{"title":"Fetch"}}