{"type":"FeatureCollection","features":[{"type":"Feature","geometry":{"type":"Point","coordinates":[31.375923195633,26.964458796524]},"properties":{"description":"","address":"Sidfa, Sodfa, Markaz Sadfa, Assiut, Egypt","title":"asssa"}}],"properties":{"description":"sasa","tags":"aaaa","title":"aaa"}}