{"type":"FeatureCollection","features":[{"type":"Feature","geometry":{"type":"Point","coordinates":[-99.901813086096,31.968598796012]},"properties":{"energy_reference":"http:\/\/www.footprinted.org\/cotton-padding4066290","co2e_reference":"http:\/\/www.footprinted.org\/cotton-fabric5731897","unit":"Kilogram","footprintmethodology":"\nCO2e factor referenced from \n(2010) Okala Design Guide 2010\n\nEnergy factor referenced from \n(1991) Comparative energy evaluation of plastic products and their alternatives for the building and construction and transportation industries\n","youtube:link":"","water":"1","energy":"27.1","co2e":"0.3","weight":"1","supplychain_instance_id":"supplychain-1","stop_instance_id":"stop-1","description":"","address":"Texas, USA","title":"Cotton -  Padding"}}],"properties":{"description":"","tags":"","title":"Dress"}}