{"type":"FeatureCollection","features":[{"type":"Feature","geometry":{"type":"Point","coordinates":[-0.66142169990793,51.907460194767]},"properties":{"youtube:link":"","water":"0","weight":"0.450","energy_reference":"http:\/\/www.footprinted.org\/high-density-polyethylene-hdpe-resin5835386","co2e_reference":"http:\/\/www.footprinted.org\/high-density-polyethylene-hdpe-resin5835386","energy":"76.7","co2e":"1.93","unit":"Kilogram","footprintmethodology":"\nCO2e factor referenced from \nHammond, G. Jones, Craig. () Embodied Carbon - the Inventory of Carbon and Energy (ICE)\n\nEnergy factor referenced from \nHammond, G. Jones, Craig. () Embodied Carbon - the Inventory of Carbon and Energy (ICE)\n","supplychain_instance_id":"supplychain-1","stop_instance_id":"stop-1","description":"","address":"Leighton Buzzard, Central Bedfordshire LU7 4FF, UK","title":"High Density Polyethylene (HDPE) Resin"}}],"properties":{"description":"","tags":"","title":"Portable Water Filter","sm:ui:tileset":"terrain"}}