{"type":"FeatureCollection","features":[{"type":"Feature","geometry":{"type":"Point","coordinates":[-159.53027777779,21.928611097097]},"properties":{"title":"KonaRed 16 oz","address":"Kalaheo, HI 96741, USA","description":"","stop_instance_id":"stop-1","supplychain_instance_id":"supplychain-1","weight":".5","co2e":"0","energy":"0","water":"1","youtube:link":"","footprintmethodology":"guessing\nWater factor referenced from \nMekonnen, M., (2010). The green, blue and grey water footprint of crops and derived crop products., Retrieved from http:\/\/www.waterfootprint.org\/Reports\/Report47-WaterFootprintCrops-Vol1.pdf\n","unit":"Kilogram"}}],"properties":{"description":"Beverage made from coffee berries and fruit juices.","tags":"","title":"KonaRed 16 oz","sm:ui:tileset":"satellite"}}