{"type":"FeatureCollection","features":[{"type":"Feature","geometry":{"type":"Point","coordinates":[104.19539698549,35.861659995661]},"properties":{"supplychain_instance_id":"supplychain-1","stop_instance_id":"stop-1","description":"","address":"China","title":"china"}}],"properties":{"description":"Emergency cooking stove","tags":"","title":"MIC-STOVE","sm:ui:tileset":"terrain"}}