{"type":"FeatureCollection","features":[{"type":"Feature","geometry":{"type":"Point","coordinates":[-95.712890986677,37.090239995559]},"properties":{"youtube:link":"","water":"0","energy":"0","co2e":"0","weight":"1","supplychain_instance_id":"supplychain-1","stop_instance_id":"stop-1","description":"","address":"United States","title":"rice"}}],"properties":{"description":"","tags":"","title":"test"}}