{"type":"FeatureCollection","features":[{"type":"Feature","geometry":{"type":"Point","coordinates":[-81.378446988672,40.798947295283]},"properties":{"title":"Stud- Tape Headquarters","address":"Canton, OH, USA","description":"Canton, OH is the location of Stud-Tape Headquarters. The company was founded in 2011.","stop_instance_id":"stop-1","supplychain_instance_id":"supplychain-1","weight":"0","co2e":"0","energy":"0","water":"0","youtube:link":""}}],"properties":{"description":"Stud-Tape\u2122, a no stretch, clear adhesive measuring tape acts as a building guide with incremental markings following construction standards for a variety of projects. The ruled measuring tape adheres along the top plate, with clear markings indicating exactly where studs are to be positioned. This makes it easy for construction crews to create precise layouts for roofs, floors, and wall studs more quickly and accurately than ever before. ","tags":"","title":"Stud-Tape"}}