{"type":"FeatureCollection","features":[{"type":"Feature","geometry":{"type":"Point","coordinates":[-71.261703,42.085701]},"properties":{"url:moreinfo":"http:\/\/foodtree.com\/sources\/5196","urltitle:moreinfo":"Please visit Lawton's Family Farm on Foodtree","address":"70 North Street, Foxboro, MA, USA","title":"Lawton's Family Farm"}},{"type":"Feature","geometry":{"type":"Point","coordinates":[-72.218803,42.333]},"properties":{"url:moreinfo":"http:\/\/foodtree.com\/sources\/5190","urltitle:moreinfo":"Please visit Chestnut Farms on Foodtree","address":"404 Turkey Street, Hardwick, MA, USA","title":"Chestnut Farms"}},{"type":"Feature","geometry":{"type":"Point","coordinates":[-72.446667,44.866667]},"properties":{"url:moreinfo":"http:\/\/foodtree.com\/sources\/5144","urltitle:moreinfo":"Please visit Spring Brook Farm on Foodtree","address":"591 Great Road,  Westfield, Vermont, USA","title":"Spring Brook Farm"}},{"type":"Feature","geometry":{"type":"Point","coordinates":[-71.172302,42.247002]},"properties":{"url:moreinfo":"http:\/\/foodtree.com\/sources\/2446","urltitle:moreinfo":"Please visit Dedham Farmers Market on Foodtree","address":"Lawn outside First Church, 670 High Street, Dedham, MA 02026, USA","title":"Dedham Farmers Market"}}],"properties":{"title":"Dedham Farmers Market"}}