{"type":"FeatureCollection","features":[{"type":"Feature","geometry":{"type":"Point","coordinates":[-83.508705888375,42.784028895155]},"properties":{"description":"","address":"Diane, Springfield, MI 48350, USA","title":"Diane"}}],"properties":{"description":"","tags":"","title":"Test"}}