{"type":"FeatureCollection","features":[{"type":"Feature","geometry":{"type":"Point","coordinates":[-122.400002,37.784302]},"properties":{"url:moreinfo":"http:\/\/foodtree.com\/sources\/7698","urltitle:moreinfo":"Please visit The Fancy Food Show on Foodtree","address":"747 Howard Street, Moscone Center, San Francisco, California, USA","title":"The Fancy Food Show"}},{"type":"Feature","geometry":{"type":"Point","coordinates":[-90.1856,44.649799]},"properties":{"url:moreinfo":"http:\/\/foodtree.com\/sources\/7956","urltitle:moreinfo":"Please visit Figi's Business Services, Inc. on Foodtree","address":"3200 S Central Avenue, Marshfield, United States","title":"Figi's Business Services, Inc."}}],"properties":{"title":"Figi's Business Services, Inc."}}