{"type":"FeatureCollection","features":[{"type":"Feature","geometry":{"type":"Point","coordinates":[121.4737039831,31.230392996084]},"properties":{"youtube:link":"","water":"0","energy":"0","co2e":"0","weight":"0","supplychain_instance_id":"supplychain-1","stop_instance_id":"stop-1","description":"Supplier","address":"Shanghai, China","title":"Shanghai, China"}}],"properties":{"description":"","tags":"","title":"Lipstick"}}