{"type":"FeatureCollection","features":[{"type":"Feature","geometry":{"type":"Point","coordinates":[-79.365997,43.683102]},"properties":{"url:moreinfo":"http:\/\/foodtree.com\/sources\/769","urltitle:moreinfo":"Please visit Evergreen Brick Works Farmers Market on Foodtree","address":"550 Bayview Avenue, Toronto, Ontario, M4W 3X8, Canada","title":"Evergreen Brick Works Farmers Market"}},{"type":"Feature","geometry":{"type":"Point","coordinates":[-79.387398,43.701401]},"properties":{"url:moreinfo":"http:\/\/foodtree.com\/sources\/1055","urltitle:moreinfo":"Please visit Oikos Tea on Foodtree","address":"501 Mount Pleasant Rd, Toronto, Ontario, Canada","title":"Oikos Tea"}}],"properties":{"title":"Oikos Tea"}}