{"type":"FeatureCollection","features":[{"type":"Feature","geometry":{"type":"Point","coordinates":[114.02240298413,22.651579997011]},"properties":{"supplychain_instance_id":"supplychain-1","stop_instance_id":"stop-47","description":"","address":"Longhua, Bao'an, Shenzhen, China, 518109","title":"Production Assembly: Foxconn"}},{"type":"Feature","geometry":{"type":"Point","coordinates":[121.4329999831,24.966699996744]},"properties":{"youtube:link":"","water":"0","energy":"0","co2e":"0","weight":"0","supplychain_instance_id":"supplychain-1","stop_instance_id":"stop-25","description":"","address":"Tucheng District, New Taipei, Taiwan 236","title":"Control: Foxconn HQ (Hong Hai Precision Industry)"}},{"type":"Feature","geometry":{"type":"Point","coordinates":[121.49999998309,25.116699996728]},"properties":{"youtube:link":"","water":"0","energy":"0","co2e":"0","weight":"0","supplychain_instance_id":"supplychain-1","stop_instance_id":"stop-4","description":"","address":"Beitou District, Taipei City, Taiwan 112","title":"Control: Pegatron HQ"}},{"type":"Feature","geometry":{"type":"Point","coordinates":[-122.02968368301,37.33085249554]},"properties":{"youtube:link":"","water":"0","energy":"0","co2e":"0","weight":"0","supplychain_instance_id":"supplychain-1","stop_instance_id":"stop-1","description":"","address":"1 Infinite Loop, Cupertino, CA 95014, USA","title":"Control: Apple HQ"}}],"properties":{"description":"","tags":"","title":"iPhone Commodity Chains","category":"41","sm:ui:tileset":"cloudmade"}}