{"type":"FeatureCollection","features":[{"type":"Feature","geometry":{"type":"Point","coordinates":[-74.005973089698,40.714352795289]},"properties":{"description":"","address":"New York, NY, USA","title":"C"}},{"type":"Feature","geometry":{"type":"Point","coordinates":[-95.36938958672,29.76019269623]},"properties":{"title":"Me","address":"Houston, TX, USA","description":""}}],"properties":{"description":"","tags":"","title":"Midterm"}}