{"type":"FeatureCollection","features":[{"type":"Feature","geometry":{"type":"Point","coordinates":[-122.392998,37.795502]},"properties":{"url:moreinfo":"http:\/\/foodtree.com\/sources\/1094","urltitle:moreinfo":"Please visit Ferry Plaza Farmers Market on Foodtree","address":"One Ferry Building, San Francisco, CA, 94111, USA","title":"Ferry Plaza Farmers Market"}},{"type":"Feature","geometry":{"type":"Point","coordinates":[-122.393997,37.7953]},"properties":{"url:moreinfo":"http:\/\/foodtree.com\/sources\/1214","urltitle:moreinfo":"Please visit Snyders Honey on Foodtree","address":"1 Ferry Building Marketplace, San Francisco, CA, 94111, USA","title":"Snyders Honey"}}],"properties":{"title":"Snyders Honey"}}