{"type":"FeatureCollection","features":[{"type":"Feature","geometry":{"type":"Point","coordinates":[-122.441002,37.7994]},"properties":{"url:moreinfo":"http:\/\/foodtree.com\/sources\/2151","urltitle:moreinfo":"Please visit The Republic on Foodtree","address":"3213 Scott Street, Marina \/ Presidio, San Francisco, California, 94123, United States","title":"The Republic"}}],"properties":{"title":"The Republic"}}