{"type":"FeatureCollection","features":[{"type":"Feature","geometry":{"type":"Point","coordinates":[-123.1157,49.28521]},"properties":{"url:moreinfo":"http:\/\/foodtree.com\/sources\/84531","urltitle:moreinfo":"Please visit Cascade Snacks on Foodtree","address":"775 West Pender Street, Vancouver, BC, Canada","title":"Cascade Snacks"}},{"type":"Feature","geometry":{"type":"Point","coordinates":[-123.130565,49.261591]},"properties":{"url:moreinfo":"http:\/\/foodtree.com\/sources\/84491","urltitle:moreinfo":"Please visit Greens on 11th on Foodtree","address":"1152 11th Avenue, Vancouver, BC, Canada","title":"Greens on 11th"}},{"type":"Feature","geometry":{"type":"Point","coordinates":[-123.098058,49.262948]},"properties":{"url:moreinfo":"http:\/\/foodtree.com\/sources\/84471","urltitle:moreinfo":"Please visit Local Eats on Foodtree","address":"335 East Broadway, vancouver, BC, Canada","title":"Local Eats"}}],"properties":{"title":"Local Eats - connections"}}