{"type":"FeatureCollection","features":[{"type":"Feature","geometry":{"type":"Point","coordinates":[-123.130565,49.261591]},"properties":{"url:moreinfo":"http:\/\/foodtree.com\/sources\/84491","urltitle:moreinfo":"Please visit Greens on 11th on Foodtree","address":"1152 11th Avenue, Vancouver, BC, Canada","title":"Greens on 11th"}},{"type":"Feature","geometry":{"type":"Point","coordinates":[-122.236924,49.068635]},"properties":{"url:moreinfo":"http:\/\/foodtree.com\/sources\/84451","urltitle:moreinfo":"Please visit Pleasant Ranch on Foodtree","address":"Upper Ten Oaks, Abbotsford, BC, Canada","title":"Pleasant Ranch"}}],"properties":{"title":"Pleasant Ranch"}}