{"type":"FeatureCollection","features":[{"type":"Feature","geometry":{"type":"Point","coordinates":[-123.063004,49.279701]},"properties":{"url:moreinfo":"http:\/\/foodtree.com\/sources\/269","urltitle:moreinfo":"Please visit Farmstead Wines on Foodtree","address":"633 Pennsylvania Ave. NW, Washington DC, DC, 20004, United States","title":"Farmstead Wines"}},{"type":"Feature","geometry":{"type":"Point","coordinates":[7.954168,44.63673]},"properties":{"url:moreinfo":"http:\/\/foodtree.com\/sources\/84441","urltitle:moreinfo":"Please visit Agricola Gian Piero Marrone on Foodtree","address":"Frazione Annunziata, 13, Annunziata, CN, 12064, Italy","title":"Agricola Gian Piero Marrone"}}],"properties":{"title":"Agricola Gian Piero Marrone"}}