{"type":"FeatureCollection","features":[{"type":"Feature","geometry":{"type":"Point","coordinates":[-72.027608789974,44.41601639506]},"properties":{"description":"","address":"Factory, St Johnsbury, VT 05819, USA","title":"mumbai"}}],"properties":{"description":"SC","tags":"sc","title":"Supply Chain"}}