{"type":"FeatureCollection","features":[{"type":"Feature","geometry":{"type":"Point","coordinates":[-81.644518988635,28.802491796329]},"properties":{"youtube:link":"","water":"0","energy":"0","co2e":"0","weight":"0","supplychain_instance_id":"supplychain-1","stop_instance_id":"stop-1","description":"Kitchen Craft Cookware is the original waterless cookware company manufactured in West Bend, Wisconsin from a green certified manufacturing plant, 100 percent American made and comes with a lifetime warranty.\r\n","address":"Mt Dora, FL, USA","title":"Kitchen Craft Cookware"}}],"properties":{"description":"Kitchen Craft Cookware is the original waterless cookware company manufactured in West Bend, Wisconsin from a green certified manufacturing plant, 100 percent American made and comes with a lifetime warranty.\n","tags":"","title":"Kitchen Craft Cookware"}}