{"type":"FeatureCollection","features":[{"type":"Feature","geometry":{"type":"Point","coordinates":[-72.976797489842,41.343365095247]},"properties":{"youtube:link":"http:\/\/www.youtube.com\/user\/AllConditionsUS","water":"0","energy":"0","co2e":"0","weight":"0","supplychain_instance_id":"supplychain-1","stop_instance_id":"stop-1","description":"Over the last 45 years, PFC cases have been used by hundreds of American manufacturers to package and protect more than 5,000 different products. Now, with the introduction of our new AllConditions\u2122 weather-resistant cases, retail consumers can take advantage of our years of experience and buy protective cases direct to meet their own individual needs.\r\n\r\nAt PFC, we do everything here in the U.S \u2013 design, mold engineering, and manufacturing. We source our materials domestically, we don\u2019t subcontract work to other companies, and we don\u2019t outsource anything to foreign manufacturers. ","address":"20 S Bradley Rd, Woodbridge, CT 06525, USA","title":"Manufactured"}}],"properties":{"description":"Over the last 45 years, PFC cases have been used by hundreds of American manufacturers to package and protect more than 5,000 different products. Now, with the introduction of our new AllConditions\u2122 weather-resistant cases, retail consumers can take advantage of our years of experience and buy protective cases direct to meet their own individual needs.","tags":"","title":"AllConditions Cases"}}