{"type":"FeatureCollection","features":[{"type":"Feature","geometry":{"type":"Point","coordinates":[-87.672203,41.922309]},"properties":{"url:moreinfo":"http:\/\/foodtree.com\/sources\/46201","urltitle:moreinfo":"Please visit Vosges Haut-Chocolat on Foodtree","address":"2211 N Elston Ave, ste 203, Chicago,  Illinois, \u00a060614","title":"Vosges Haut-Chocolat"}},{"type":"Feature","geometry":{"type":"Point","coordinates":[-115.173336,36.119556]},"properties":{"url:moreinfo":"http:\/\/foodtree.com\/sources\/84611","urltitle:moreinfo":"Please visit Vosges Haut-Chocolat Las Vegas Boutique on Foodtree","address":"3500 Las Vegas Blvd South\u00a0 , Forum Shops, Suite R04 , Las Vegas , NV\u00a0 , 89109 , United States","title":"Vosges Haut-Chocolat Las Vegas Boutique"}}],"properties":{"title":"Vosges Haut-Chocolat Las Vegas Boutique"}}