{"type":"FeatureCollection","features":[{"type":"Feature","geometry":{"type":"Point","coordinates":[-93.097701987038,41.878002495212]},"properties":{"description":"","address":"Iowa, USA","title":"Iowa"}}],"properties":{"description":"Mixing of Synthetic rubber with EPDM, fillers, oils and carbon black","tags":"","title":"Rubber"}}