{"type":"FeatureCollection","features":[{"type":"Feature","geometry":{"type":"Point","coordinates":[104.19539698549,35.861659995661]},"properties":{"title":"steel","address":"China","description":"","stop_instance_id":"stop-1","supplychain_instance_id":"supplychain-1","weight":"0","co2e":"0","energy":"0","water":"0","youtube:link":""}}],"properties":{"description":"","tags":"","title":"black creek arrow","sm:ui:tileset":"satellite"}}