{"type":"FeatureCollection","features":[{"type":"Feature","geometry":{"type":"Point","coordinates":[-119.41793238338,36.778260995585]},"properties":{"youtube:link":"","water":"0","energy":"0","co2e":"0","weight":"0","supplychain_instance_id":"supplychain-1","stop_instance_id":"stop-5","description":"the first point where phone was made","address":"California, USA","title":"california"}}],"properties":{"description":"The story behind a ballpont pen ","tags":"","title":"Soccer ball Map"}}