{"type":"FeatureCollection","features":[{"type":"Feature","geometry":{"type":"Point","coordinates":[120.96051498316,23.697809996889]},"properties":{"youtube:link":"","water":"0","energy":"0","co2e":"0","weight":"0","supplychain_instance_id":"supplychain-1","stop_instance_id":"stop-11","description":"AcBel Polytech Inc.","address":"Taiwan","title":"Power Adapter"}},{"type":"Feature","geometry":{"type":"Point","coordinates":[120.11383468328,31.711267596037]},"properties":{"youtube:link":"","water":"0","energy":"0","co2e":"0","weight":"0","supplychain_instance_id":"supplychain-1","stop_instance_id":"stop-4","description":"AAC is the worldwide leading Micro Component Total Solutions provider for communications and consumer electronics market.","address":"3\u53f7 Xinsheng Rd, Wujin, Changzhou, Jiangsu, China, 213103","title":"Parts Supplier"}},{"type":"Feature","geometry":{"type":"Point","coordinates":[-81.211747288696,35.575688895685]},"properties":{"supplychain_instance_id":"supplychain-1","stop_instance_id":"stop-1","description":"","address":"Maiden, NC, USA","title":"Data Center"}}],"properties":{"description":"This sourcemap outlines the complete production and distribution of Apple Macbook laptop computers.","tags":"computer macbook apple production distribution","title":"Apple Macbook Distribution"}}