{"type":"FeatureCollection","features":[{"type":"Feature","geometry":{"type":"Point","coordinates":[118.14589898356,24.512325996796]},"properties":{"youtube:link":"","water":"0","energy":"0","co2e":"0","weight":"1.35","supplychain_instance_id":"supplychain-1","stop_instance_id":"stop-1","description":"Toilet seats are made here and exported to Eastern Europe, North America, Mid East\/Africa, Central\/South America, Asia, Western Europe, Australasia","address":"Huli, Xiamen, Fujian, China","title":" Oceanwell (Xiamen) Industrial Co., Ltd."}}],"properties":{"description":"","tags":"","title":"American Standard Toilet","sm:ui:weight":"1"}}