{"type":"FeatureCollection","features":[{"type":"Feature","geometry":{"type":"Point","coordinates":[-94.492452986846,39.202502995397]},"properties":{"youtube:link":"","water":"0","energy":"0","co2e":"0","weight":"0","supplychain_instance_id":"supplychain-1","stop_instance_id":"stop-5","description":"This is another place where Ford puts together their Ford F-150","address":"Claycomo, MO, USA","title":"Ford F-150 (2)"}},{"type":"Feature","geometry":{"type":"Point","coordinates":[-83.176314488422,42.322259895184]},"properties":{"youtube:link":"","water":"0","energy":"0","co2e":"0","weight":"0","supplychain_instance_id":"supplychain-1","stop_instance_id":"stop-1","description":"This is where the Ford is put together","address":"Dearborn, MI, USA","title":"2009 Ford F-150"}}],"properties":{"description":"Where the 2009 Ford F-150 is put together.","tags":"ford truck f150","title":"2009 Ford F-150"}}