{"type":"FeatureCollection","features":[{"type":"Feature","geometry":{"type":"Point","coordinates":[-85.668086288075,42.963359895144]},"properties":{"description":"","address":"Grand Rapids, MI, USA","title":"Grand Rapids, Michigan"}},{"type":"Feature","geometry":{"type":"Point","coordinates":[-83.687456188351,43.012527395141]},"properties":{"description":"","address":"Flint, MI, USA","title":"Flint Michigan"}},{"type":"Feature","geometry":{"type":"Point","coordinates":[-83.04575378844,42.331426995183]},"properties":{"supplychain_instance_id":"supplychain-1","stop_instance_id":"stop-1","description":"","address":"Detroit, MI, USA","title":"Detroit, Michigan"}}],"properties":{"title":"Local Aquaculture Systems","description":"","tags":""}}