{"type":"FeatureCollection","features":[{"type":"Feature","geometry":{"type":"Point","coordinates":[-1.537385199786,47.218807794923]},"properties":{"description":"","address":"Manufacture, 44000 Nantes, France","title":"Manufacture"}}],"properties":{"title":"SC kits","description":"","tags":""}}