{"type":"FeatureCollection","features":[{"type":"Feature","geometry":{"type":"Point","coordinates":[10.786546098498,52.422650294756]},"properties":{"youtube:link":"","water":"0","energy":"0","co2e":"0","weight":"0","supplychain_instance_id":"supplychain-1","stop_instance_id":"stop-9","description":"","address":"Wolfsburg, Germany","title":"Volkswagen Headuarters"}},{"type":"Feature","geometry":{"type":"Point","coordinates":[13.07269099818,52.394188694757]},"properties":{"supplychain_instance_id":"supplychain-1","stop_instance_id":"stop-4","description":"","address":"Potsdam, Germany","title":"Volkswagen Design Center"}},{"type":"Feature","geometry":{"type":"Point","coordinates":[-98.206199586331,19.041296697447]},"properties":{"supplychain_instance_id":"supplychain-1","stop_instance_id":"stop-1","description":"","address":"Puebla, Mexico","title":"Volkswagen Assembly Plant"}}],"properties":{"title":"Volkswagen Jetta, U.S. consumption","description":"","tags":""}}