{"type":"FeatureCollection","features":[{"type":"Feature","geometry":{"type":"Point","coordinates":[-118.24740968354,34.028877295821]},"properties":{"supplychain_instance_id":"supplychain-1","stop_instance_id":"stop-4","description":"","address":"1213 E 14th St, Los Angeles, CA 90021, USA","title":"LAmade Headquarters"}}],"properties":{"sm:ui:tileset":"cloudmade","title":"LAmade Clothing","description":"Made in the USA","tags":""}}