{"type":"FeatureCollection","features":[{"type":"Feature","geometry":{"type":"Point","coordinates":[-80.782126988755,8.5379809988203]},"properties":{"description":"","address":"Panama","title":"PANAMA"}}],"properties":{"title":"PANAMA LINE","description":"3PL SERVICE LOCATED IN COLON FREE ZONE AND\nPANEXPORT FREE ZONE  REPUBLIC OF PANAMA","tags":"logisistics in panama"}}