{"type":"FeatureCollection","features":[{"type":"Feature","geometry":{"type":"Point","coordinates":[-122.80371018291,45.487061995004]},"properties":{"description":"","address":"Beaverton, OR, USA","title":"Si\u00e8ge social"}}],"properties":{"title":"Les chaussures de sports \u00e0 travers la mondialisation","description":"","tags":""}}