{"type":"FeatureCollection","features":[{"type":"Feature","geometry":{"type":"Point","coordinates":[-117.85311188359,33.787794395843]},"properties":{"description":"","address":"Orange, CA, USA","title":"Orange"}}],"properties":{"title":"Orange","description":"","tags":""}}