{"type":"FeatureCollection","features":[{"type":"Feature","geometry":{"type":"Point","coordinates":[-99.981437986083,20.391527997282]},"properties":{"description":"","address":"San Juan del R\u00edo, Quer\u00e9taro, Mexico","title":"Imbera"}}],"properties":{"title":"Imbera Cooling","description":"","tags":"refrigerator"}}