{"type":"FeatureCollection","features":[{"type":"Feature","geometry":{"type":"Point","coordinates":[3.4975789995131,50.185435994813]},"properties":{"supplychain_instance_id":"supplychain-1","stop_instance_id":"stop-4","description":"","address":"Solesmes, France","title":"solesmes 59730"}},{"type":"Feature","geometry":{"type":"Point","coordinates":[117.20098298369,39.084157995405]},"properties":{"supplychain_instance_id":"supplychain-1","stop_instance_id":"stop-1","description":"","address":"Tianjin, China","title":"tianjing"}}],"properties":{"sm:ui:tileset":"terrain","title":"calcium metal","description":"","tags":""}}