{"type":"FeatureCollection","features":[{"type":"Feature","geometry":{"type":"Point","coordinates":[72.856177999999,19.017655999998]},"properties":{"1":"Mumbai, Maharashtra, India","unit":"kg","weight":"10","co2e":"3.76","qty":"10","title":"Particle Board ","address":"Mumbai, Maharashtra, India","name":"Particle Board ","description":""}},{"type":"Feature","geometry":{"type":"Point","coordinates":[104.195397,35.861660000001]},"properties":{"1":"China","unit":"kg","weight":"1","co2e":"4.2","qty":"1","title":"Hemp Fiber Composite","address":"China","name":"Hemp Fiber Composite","description":""}}],"properties":{"alias:preferred":"test-project","description":"Created on February 24, 2010 by johndoe2611 on Sourcemap.org:\n\njust a test project","distance:transport":"19512.3","emissions:embodied":"41.8","emissions:total":"44.1083","emissions:transport":"2.3083","legacy:creator":"7462","legacy:distance":"19512.3","legacy:emissions":"2.3083","legacy:oid":"2244","sm:migrated:time":"1313858040","sm:ui:co2e":"1","sm:ui:weight":"1","title":"test project","weight":"11","tags":""}}