{"type":"FeatureCollection","features":[{"type":"Feature","geometry":{"type":"Point","coordinates":[113.92132698414,-0.78927499989015]},"properties":{"youtube:link":"","water":"0","energy":"0","co2e":"0","weight":"0","supplychain_instance_id":"supplychain-1","stop_instance_id":"stop-1","description":"","address":"Indonesia","title":"Rubber, leather, plastic"}}],"properties":{"title":"Nike Footwear Commodity Chain","description":"","tags":""}}