{"type":"FeatureCollection","features":[{"type":"Feature","geometry":{"type":"Point","coordinates":[-122.27111368298,37.804363695503]},"properties":{"supplychain_instance_id":"supplychain-1","stop_instance_id":"stop-1","description":"","address":"Oakland, CA, USA","title":"Pepperoni Pizza, Oakland,CA"}}],"properties":{"sm:ui:co2e":"1","title":"Pepperoni Pizza","description":"","tags":""}}