{"type":"FeatureCollection","features":[{"type":"Feature","geometry":{"type":"Point","coordinates":[-99.129121786198,19.478700597393]},"properties":{"description":"","address":"Prueba, Industrial, Gustavo A. Madero, 07800 Mexico City, Federal District, Mexico","title":"Probando"}}],"properties":{"title":"Prueba","description":"Es un mapa de prueba","tags":""}}