{"type":"FeatureCollection","features":[{"type":"Feature","geometry":{"type":"Point","coordinates":[-134.99999998121,-82.862751897251]},"properties":{"description":"","address":"Antarctica","title":"Lauren was here"}},{"type":"Feature","geometry":{"type":"Point","coordinates":[-74.799474989588,42.102615995197]},"properties":{"description":"","address":"539 Perch Lake Road, Andes, NY 13731, USA","title":"Dirty Girl Farm"}},{"type":"Feature","geometry":{"type":"Point","coordinates":[-75.491850489491,43.786735995096]},"properties":{"title":"Kraft Philadelphia Cream Cheese","address":"Lowville, NY 13367, USA","description":"","stop_instance_id":"stop-3","supplychain_instance_id":"supplychain-1","weight":"0","co2e":"0","energy":"0","water":"0","youtube:link":""}},{"type":"Feature","geometry":{"type":"Point","coordinates":[-88.837328987634,43.457769195115]},"properties":{"title":"Kraft Philadelphia Cream Cheese","address":"Beaver Dam, WI 53916, USA","description":""}}],"properties":{"tags":"","description":"","title":"Kraft Cream Cheese and Dirty Girls goat cheese"}}