{"type":"FeatureCollection","features":[{"type":"Feature","geometry":{"type":"Point","coordinates":[-4.144978799423,30.765231796129]},"properties":{"youtube:link":"http:\/\/www.youtube.com\/watch?v=dMqdWoMnZvA","water":"0","energy":"0","co2e":"0","weight":"0","supplychain_instance_id":"supplychain-1","stop_instance_id":"stop-3","description":"Sahara Oasis & Sands - Ouzina desert tours, Ouzina camel treks, Sahara New Years fiest, Services in sahara - Morocco travel, the beauty of Morocco, Porte De Sahara, Sahara video, Adventures in Morocco, special Morocco, Bivouac desert camp in Morocco, Kasbah Morocco, Sahara taouz, GPS sahara Morocco, Ouzina Maroc, Voyage Sahara, Touareg Morocco, Kser Morocco, sahara desert Magic...\r\nhttp:\/\/www.portedesahara.com\/","address":"Ouzina, Morocco","title":"Ouzina Morocco : Auberge Porte De Sahara"}},{"type":"Feature","geometry":{"type":"Point","coordinates":[-8.0140036988845,31.627236196045]},"properties":{"title":"viajes a Marruecos, Morocco4x4","address":"Avenue Mohammed VI, Marrakesh, Morocco","description":"Viajes tem\u00e1ticos a Marruecos: a medida ,Grupos,Novios,Navidad,Semana Santa,Luna de Miel, Familias,Trekking y Senderismo,Terap\u00e9uticos, Fotogr\u00e1ficos, Estudiantes.","stop_instance_id":"stop-1","supplychain_instance_id":"supplychain-1","weight":"0","co2e":"0","energy":"0","water":"0","youtube:link":"http:\/\/www.youtube.com\/watch?v=odQ4tc_B2qQ"}}],"properties":{"tags":"travel agency, agencia de viajes","description":"Excursiones por Marruecos, rutas marruecos, rutas 4x4 marruecos, tours de marrakech a merzouga, viajar a marruecos , viajes a marruecos, rutas en 4x4","title":"viajes a Marruecos, Morocco4x4"}}