{"type":"FeatureCollection","features":[{"type":"Feature","geometry":{"type":"Point","coordinates":[-71.474588090051,42.086760795199]},"properties":{"description":"","address":"Bellingham, MA, USA","title":"Distribution Center"}}],"properties":{"title":"Bagasse","description":"","tags":""}}