{"type":"FeatureCollection","features":[{"type":"Feature","geometry":{"type":"Point","coordinates":[-95.36938958672,29.76019269623]},"properties":{"flickr:setid":"","youtube:link":"https:\/\/www.youtube.com\/watch?v=qPr0BSxaoT8","water":"0","energy":"4","co2e":"3","weight":"1000","supplychain_instance_id":"supplychain-1","stop_instance_id":"stop-13","description":"","address":"Houston, TX, USA","title":"Farming"}},{"type":"Feature","geometry":{"type":"Point","coordinates":[-97.743060786391,30.267152996179]},"properties":{"youtube:link":"","water":"0","energy":"0","co2e":"0","weight":"0","supplychain_instance_id":"supplychain-1","stop_instance_id":"stop-1","description":"48,000 head capacity","address":"Austin, TX, USA","title":"Freeyard"}}],"properties":{"title":"Texas Beef","description":"Here is it.","tags":""}}