{"type":"FeatureCollection","features":[{"type":"Feature","geometry":{"type":"Point","coordinates":[-43.940646493883,-19.923705997339]},"properties":{"flickr:setid":"","water":"0","energy":"0","co2e":"0","weight":"0","supplychain_instance_id":"supplychain-1","stop_instance_id":"stop-1","description":"","address":"Avenida Augusto de Lima, 580 - Centro, Belo Horizonte - Minas Gerais, 30190-001, Brazil","title":"Terreno"}}],"properties":{"title":"Edif\u00edcio garagem","description":"","tags":""}}