{"type":"FeatureCollection","features":[{"type":"Feature","geometry":{"type":"Point","coordinates":[-3.4359729999961,55.378051000001]},"properties":{"description":"","unit":"kg","weight":"0.2","co2e":"0","qty":"0.2","title":"Garlic","address":"United Kingdom","name":"Garlic","1":"United Kingdom"}},{"type":"Feature","geometry":{"type":"Point","coordinates":[-3.7492200000004,40.463667000002]},"properties":{"description":"","unit":"kg","weight":"0.1","co2e":"0","qty":"0.1","title":"Lemon","address":"Spain","name":"Lemon","1":"Spain"}},{"type":"Feature","geometry":{"type":"Point","coordinates":[78.962879999997,20.593684000004]},"properties":{"description":"","unit":"kg","weight":"0.5","co2e":"0","qty":"0.5","title":"Chickpeas","address":"India","name":"Chickpeas","1":"India"}}],"properties":{"alias:preferred":"hummus","description":"Created on May 24, 2010 by stephendl on Sourcemap.org.","distance:transport":"19562.45","emissions:embodied":"0","emissions:total":"0","emissions:transport":"0","legacy:creator":"9703","legacy:distance":"19562.45","legacy:emissions":"0","legacy:oid":"3761","sm:migrated:time":"1313857933","sm:ui:weight":"1","tags":"","title":"Hummus","weight":"0.8"}}