{"type":"FeatureCollection","features":[{"type":"Feature","geometry":{"type":"Point","coordinates":[-89.016613487609,45.310171695014]},"properties":{"description":"","address":"A, Deerbrook, WI 54424, USA","title":"aa"}}],"properties":{"title":"Korean Education","description":"Korean Education","tags":"korean education"}}