{"type":"FeatureCollection","features":[{"type":"Feature","geometry":{"type":"Point","coordinates":[4.8951678993186,52.370215694757]},"properties":{"description":"","address":"Amsterdam, The Netherlands","title":"DC "}},{"type":"Feature","geometry":{"type":"Point","coordinates":[-0.11982439998332,51.511213894776]},"properties":{"supplychain_instance_id":"supplychain-1","stop_instance_id":"stop-1","description":"","address":"London, UK","title":"DC"}}],"properties":{"sm:ui:weight":"1","sm:ui:water":"1","sm:ui:energy":"1","sm:ui:co2e":"1","title":"chain","description":"","tags":""}}