{"type":"FeatureCollection","features":[{"type":"Feature","geometry":{"type":"Point","coordinates":[83.564728288368,21.875044597103]},"properties":{"description":"","address":"Jamga Station, Jamgaon, Chhattisgarh 496197, India","title":"JMG"}},{"type":"Feature","geometry":{"type":"Point","coordinates":[83.564728288368,21.875044597103]},"properties":{"supplychain_instance_id":"supplychain-1","stop_instance_id":"stop-10","description":"","address":"Jamga Station, Jamgaon, Chhattisgarh 496197, India","title":"JMG"}},{"type":"Feature","geometry":{"type":"Point","coordinates":[83.564728288368,21.875044597103]},"properties":{"supplychain_instance_id":"supplychain-1","stop_instance_id":"stop-1","description":"","address":"Jamga Station, Jamgaon, Chhattisgarh 496197, India","title":"JMG"}}],"properties":{"title":"MJG","description":"","tags":""}}