{"type":"FeatureCollection","features":[{"type":"Feature","geometry":{"type":"Point","coordinates":[104.19539698549,35.861659995661]},"properties":{"description":"","address":"China","title":"China"}},{"type":"Feature","geometry":{"type":"Point","coordinates":[25.013606996518,58.595271994726]},"properties":{"supplychain_instance_id":"supplychain-1","stop_instance_id":"stop-1","description":"","address":"Estonia","title":"Estonia"}}],"properties":{"title":"downjackets","description":"","tags":""}}