{"type":"FeatureCollection","features":[{"type":"Feature","geometry":{"type":"Point","coordinates":[45.079161993725,23.885941996868]},"properties":{"description":"","address":"Saudi Arabia","title":"dairy"}},{"type":"Feature","geometry":{"type":"Point","coordinates":[104.19539698549,35.861659995661]},"properties":{"supplychain_instance_id":"supplychain-1","stop_instance_id":"stop-79","description":"","address":"China","title":"dairy"}},{"type":"Feature","geometry":{"type":"Point","coordinates":[-95.712890986677,37.090239995559]},"properties":{"supplychain_instance_id":"supplychain-1","stop_instance_id":"stop-74","description":"","address":"United States","title":"dairy "}},{"type":"Feature","geometry":{"type":"Point","coordinates":[78.962879989009,20.593683997257]},"properties":{"supplychain_instance_id":"supplychain-1","stop_instance_id":"stop-71","description":"","address":"India","title":"dairy"}}],"properties":{"title":"geography thing","description":"aalskdfljal;g","tags":""}}