{"type":"FeatureCollection","features":[{"type":"Feature","geometry":{"type":"Point","coordinates":[-118.2436849,34.052234200001]},"properties":{"1":"Los Angeles, CA, USA","unit":"kg","weight":"0","co2e":"0","qty":"0","title":"Denim Sold","address":"Los Angeles, CA, USA","name":"Denim Sold","description":""}},{"type":"Feature","geometry":{"type":"Point","coordinates":[104.195397,35.861660000001]},"properties":{"1":"China","unit":"kg","weight":"0","co2e":"0","qty":"0","title":"Denim Factory","address":"China","name":"Denim Factory","description":""}}],"properties":{"alias:preferred":"paige-premium-denim","description":"Created on February 25, 2010 by Lindsay Adishian on Sourcemap.org.","distance:transport":"23883.3","emissions:embodied":"0","emissions:total":"0","emissions:transport":"0","legacy:creator":"9008","legacy:distance":"23883.3","legacy:emissions":"0","legacy:oid":"3004","sm:migrated:time":"1313858022","title":"Paige Premium Denim","weight":"0","tags":""}}